.pre-commit-config.yaml
LICENSE
MANIFEST.in
README.rst
pyproject.toml
pytest.ini
requirements.txt
setup.cfg
setup.py
mafiat/__init__.py
mafiat/io.py
mafiat/plot.py
mafiat/tools.py
mafiat/twist.py
mafiat.egg-info/PKG-INFO
mafiat.egg-info/SOURCES.txt
mafiat.egg-info/dependency_links.txt
mafiat.egg-info/not-zip-safe
mafiat.egg-info/requires.txt
mafiat.egg-info/top_level.txt
mafiat/tests/__init__.py
mafiat/tests/test_twist.py
notebooks/Computing_Tg.ipynb
notebooks/Visualising_Tg.ipynb